sorting_asmaa/__init__.py
sorting_asmaa-0.4.6.dist-info/LICENSE.py
sorting_asmaa-0.4.6.dist-info/METADATA
sorting_asmaa-0.4.6.dist-info/WHEEL
sorting_asmaa-0.4.6.dist-info/top_level.txt
sorting_asmaa-0.4.6.dist-info/RECORD
