Metadata-Version: 2.1
Name: sorting-asmaa
Version: 0.4.6
Summary: A sorting  package
Home-page: https://github.com/asmaaalaa99/sorting
Author: Asmaa Aly
Author-email: asmaa.ali@minerva.kgi.edu
License: UNKNOWN
Platform: UNKNOWN
Classifier: Programming Language :: Python :: 3
Classifier: License :: OSI Approved :: MIT License
Classifier: Operating System :: OS Independent
